roarquery/__init__.py
roarquery/__main__.py
roarquery/collections.py
roarquery/py.typed
roarquery/runs.py
roarquery/utils.py
roarquery-1.0.6.dist-info/entry_points.txt
roarquery-1.0.6.dist-info/LICENSE.rst
roarquery-1.0.6.dist-info/WHEEL
roarquery-1.0.6.dist-info/METADATA
roarquery-1.0.6.dist-info/RECORD
