Metadata-Version: 2.1
Name: roarquery
Version: 1.0.6
Summary: Roarquery
Home-page: https://github.com/richford/roarquery
License: MIT
Author: Adam Richie-Halford
Author-email: richiehalford@gmail.com
Requires-Python: >=3.9,<4.0
Classifier: Development Status :: 3 - Alpha
Classifier: License :: OSI Approved :: MIT License
Classifier: Programming Language :: Python :: 3
Classifier: Programming Language :: Python :: 3.9
Classifier: Programming Language :: Python :: 3.10
Classifier: Programming Language :: Python :: 3.11
Requires-Dist: click (>=8.0.1,<9.0.0)
Requires-Dist: pandas (>=1.4.2,<2.0.0)
Requires-Dist: python-dateutil (>=2.8.2,<3.0.0)
Requires-Dist: tqdm (>=4.64.0,<5.0.0)
Project-URL: Changelog, https://github.com/richford/roarquery/releases
Project-URL: Documentation, https://roarquery.readthedocs.io
Project-URL: Repository, https://github.com/richford/roarquery
